{
  "main": {
    "id": "35dc58889efc7af6",
    "type": "split",
    "children": [
      {
        "id": "7b27e350583b42a9",
        "type": "tabs",
        "children": [
          {
            "id": "48dff2d45796c44b",
            "type": "leaf",
            "state": {
              "type": "markdown",
              "state": {
                "file": "z_Templates/TemplateNPC.md",
                "mode": "preview",
                "source": false
              }
            }
          }
        ]
      }
    ],
    "direction": "vertical"
  },
  "left": {
    "id": "ef2fa061dc384dbb",
    "type": "split",
    "children": [
      {
        "id": "776915f0f047e046",
        "type": "tabs",
        "children": [
          {
            "id": "2911de48d50d504c",
            "type": "leaf",
            "state": {
              "type": "file-explorer",
              "state": {
                "sortOrder": "alphabetical"
              }
            }
          },
          {
            "id": "f7191f1a02d83b6c",
            "type": "leaf",
            "state": {
              "type": "search",
              "state": {
                "query": "",
                "matchingCase": false,
                "explainSearch": false,
                "collapseAll": false,
                "extraContext": false,
                "sortOrder": "alphabetical"
              }
            }
          },
          {
            "id": "6da38734e1b60552",
            "type": "leaf",
            "state": {
              "type": "bookmarks",
              "state": {}
            }
          },
          {
            "id": "2e6355ae312b2c82",
            "type": "leaf",
            "pinned": true,
            "state": {
              "type": "markdown",
              "state": {
                "file": "1-DM Toolkit/DnD5e-SideScreen.md",
                "mode": "preview",
                "source": false
              },
              "pinned": true
            }
          },
          {
            "id": "f6ef017cc52d2e49",
            "type": "leaf",
            "pinned": true,
            "state": {
              "type": "markdown",
              "state": {
                "file": "1-DM Toolkit/DM Board.md",
                "mode": "preview",
                "source": true
              },
              "pinned": true
            }
          }
        ]
      }
    ],
    "direction": "horizontal",
    "width": 347.5
  },
  "right": {
    "id": "4376769ea3073bd6",
    "type": "split",
    "children": [
      {
        "id": "09384058bb1c4e72",
        "type": "tabs",
        "children": [
          {
            "id": "01866bcbc2fd8a19",
            "type": "leaf",
            "state": {
              "type": "backlink",
              "state": {
                "file": "z_Templates/TemplateNPC.md",
                "collapseAll": false,
                "extraContext": false,
                "sortOrder": "alphabetical",
                "showSearch": false,
                "searchQuery": "",
                "backlinkCollapsed": false,
                "unlinkedCollapsed": true
              }
            }
          },
          {
            "id": "505cdf32bf6b016b",
            "type": "leaf",
            "state": {
              "type": "outgoing-link",
              "state": {
                "file": "z_Templates/TemplateNPC.md",
                "linksCollapsed": false,
                "unlinkedCollapsed": false
              }
            }
          },
          {
            "id": "e0476cfc571d360e",
            "type": "leaf",
            "state": {
              "type": "tag",
              "state": {
                "sortOrder": "frequency",
                "useHierarchy": true
              }
            }
          },
          {
            "id": "734965fc2bb6a962",
            "type": "leaf",
            "state": {
              "type": "outline",
              "state": {
                "file": "z_Templates/TemplateNPC.md"
              }
            }
          },
          {
            "id": "89c85e720490d000",
            "type": "leaf",
            "state": {
              "type": "advanced-tables-toolbar",
              "state": {}
            }
          },
          {
            "id": "082d00d22d181097",
            "type": "leaf",
            "state": {
              "type": "help-mate",
              "state": {}
            }
          },
          {
            "id": "1d54d43c1cb242fe",
            "type": "leaf",
            "state": {
              "type": "all-properties",
              "state": {
                "sortOrder": "frequency",
                "showSearch": false,
                "searchQuery": ""
              }
            }
          },
          {
            "id": "bb21e6fb9beae31a",
            "type": "leaf",
            "state": {
              "type": "initiative-tracker-view",
              "state": {}
            }
          },
          {
            "id": "b17e9d619991a46b",
            "type": "leaf",
            "state": {
              "type": "DICE_ROLLER_VIEW",
              "state": {}
            }
          },
          {
            "id": "c8c0bd3a84d4d5f1",
            "type": "leaf",
            "state": {
              "type": "MAIN_VIEW",
              "state": {}
            }
          }
        ],
        "currentTab": 9
      }
    ],
    "direction": "horizontal",
    "width": 200,
    "collapsed": true
  },
  "left-ribbon": {
    "hiddenItems": {
      "command-palette:Open command palette": false,
      "switcher:Open quick switcher": false,
      "graph:Open graph view": false,
      "canvas:Create new canvas": false,
      "daily-notes:Open today's daily note": false,
      "templates:Insert template": false,
      "templater-obsidian:Templater": false,
      "obsidian-custom-frames:Open Obsidian Forum": false,
      "obsidian-leaflet-plugin:Open Leaflet Map": false,
      "initiative-tracker:Initiative Tracker Encounter Builder": false,
      "obsidian-import-json:JSON/CSV Importer": false,
      "obsidian42-brat:BRAT": false,
      "table-editor-obsidian:Advanced Tables Toolbar": false,
      "obsidian-kanban:Create new board": false,
      "helpmate:HelpMate": false,
      "obsidian-excalidraw-plugin:Create new drawing": false,
      "obsidian-5e-statblocks:Open Creature pane": false,
      "solo-rpg-toolkit:Solo RPG Toolkit": false,
      "obsidian-textgenerator-plugin:Generate Text!": false,
      "obsidian-textgenerator-plugin:Text Generator: Templates Packages Manager": false
    }
  },
  "active": "48dff2d45796c44b",
  "lastOpenFiles": [
    "z_Templates/TemplatePlayer.md",
    "1-Party/Phandelver and Below Party/Portland.md",
    "1-DM Toolkit/DM Board.md",
    "1-Party/NewPlayer.md",
    "1-Party/Phandelver and Below Party/Phandelver and Below Party.md",
    "1-Session Journals/2024-06-01.md",
    "1-DM Toolkit/Home.md",
    "README.md",
    "2-World/Lampoteuo/Lampoteuo.md",
    "New Note.md",
    "1-DM Toolkit/DnD5e-SideScreen.md",
    "1-DM Toolkit/Vault Report.md",
    "1-DM Toolkit/Travel Calculator.md",
    "1-DM Toolkit/Map Calculator.md",
    "1-DM Toolkit/PF2e-DM Screen.md",
    "1-DM Toolkit/Journey Board.md",
    "3-Mechanics/CLI/2-Mechanics/CLI/rules/skills.md",
    "1-DM Toolkit/DnD5e-DM Screen.md",
    "2-Campaign/Quests/Quests.md",
    "2-Campaign/Quests/Deliver goods to Phandalin.md",
    "2-Campaign/Quests/Warn the Midwife.md",
    "2-Campaign/Quests/Beat the Goblin.md",
    "2-World/Neverwinter.md",
    "2-World/Ruins of The Twilight Palace.md",
    "2-World/Phandalin",
    "2-World/Logger's Camp.md",
    "2-World/Lampoteuo/The Wound/The Wound.md",
    "z_Templates/4_Markdown/Call Out Boxes 2",
    "3-Mechanics/CLI/2-Mechanics/CLI/rules/variant-rules",
    "3-Mechanics/CLI/2-Mechanics/CLI/bestiary/undead",
    "3-Mechanics/CLI/2-Mechanics/CLI/bestiary/plant",
    "3-Mechanics/CLI/2-Mechanics/CLI/bestiary/ooze",
    "3-Mechanics/CLI/2-Mechanics/CLI/bestiary/npc",
    "3-Mechanics/CLI/2-Mechanics/CLI/bestiary/monstrosity",
    "3-Mechanics/CLI/2-Mechanics/CLI/bestiary/legendary-group",
    "3-Mechanics/CLI/2-Mechanics/CLI/bestiary/humanoid",
    "z_Assets/Pasted Image 20240630230819_217.png",
    "z_Assets/Pasted Image 20240630225934_265.png",
    "z_Assets/Pasted Image 20240630225910_214.png",
    "0-Scratch Notes/Untitled.canvas",
    "z_Assets/Pasted image 20240630214232.png",
    "z_Assets/Pasted Image 20240630214110_213.png",
    "z_Assets/Pasted Image 20240630214055_211.png",
    "z_Assets/Pasted Image 20240630213938_233.png",
    "z_Assets/Pasted Image 20240630213157_204.png",
    "z_Assets/Pasted Image 20240630211249_215.png",
    "z_Assets/Decks/Business Card Dungeon/Dungeon18.png",
    "Untitled.canvas"
  ]
}